[
  {
    "bounds": "",
    "size": [
      256,
      256
    ],
    "url": "http://qcricl1linuxvm2.cloudapp.net:8090/static/TestImg/IMG_1756.JPG"
  },
  {
    "bounds": "",
    "size": [
      256,
      256
    ],
    "url": "http://qcricl1linuxvm2.cloudapp.net:8090/static/TestImg/IMG_1755.JPG"
  },
  {
    "bounds": "",
    "size": [
      256,
      256
    ],
    "url": "http://qcricl1linuxvm2.cloudapp.net:8090/static/TestImg/IMG_1754.JPG"
  },
  {
    "bounds": "",
    "size": [
      256,
      256
    ],
    "url": "http://qcricl1linuxvm2.cloudapp.net:8090/static/TestImg/IMG_1753.JPG"
  },
  {
    "bounds": "",
    "size": [
      256,
      256
    ],
    "url": "http://qcricl1linuxvm2.cloudapp.net:8090/static/TestImg/IMG_1752.JPG"
  },
  {
    "bounds": "",
    "size": [
      256,
      256
    ],
    "url": "http://qcricl1linuxvm2.cloudapp.net:8090/static/TestImg/IMG_1751.JPG"
  },
  {
    "bounds": [
      125.00244140625,
      11.223530807940303,
      125.0020980834961,
      11.223194050933833
    ],
    "size": [
      256,
      256
    ],
    "url": "http://qcricl1linuxvm2.cloudapp.net:8090/static/TestImg/IMG_1750.JPG"
  },
  {
    "bounds": "",
    "size": [
      256,
      256
    ],
    "url": "http://qcricl1linuxvm2.cloudapp.net:8090/static/TestImg/IMG_1749.JPG"
  },
  {
    "bounds": "",
    "size": [
      256,
      256
    ],
    "url": "http://qcricl1linuxvm2.cloudapp.net:8090/static/TestImg/IMG_1748.JPG"
  },
  {
    "bounds": "",
    "size": [
      256,
      256
    ],
    "url": "http://qcricl1linuxvm2.cloudapp.net:8090/static/TestImg/IMG_1747.JPG"
  },
  {
    "bounds": "",
    "size": [
      256,
      256
    ],
    "url": "http://qcricl1linuxvm2.cloudapp.net:8090/static/TestImg/IMG_1746.JPG"
  }
]